README.md
setup.cfg
setup.py
asgi_s3/__init__.py
asgi_s3/__main__.py
asgi_s3/__version__.py
asgi_s3/cli.py
asgi_s3/middleware.py
asgi_s3/storage.py
asgi_s3.egg-info/PKG-INFO
asgi_s3.egg-info/SOURCES.txt
asgi_s3.egg-info/dependency_links.txt
asgi_s3.egg-info/entry_points.txt
asgi_s3.egg-info/requires.txt
asgi_s3.egg-info/top_level.txt
tests/__init__.py
tests/conftest.py
tests/test_cli.py
tests/test_middleware.py
tests/test_storage.py