Metadata-Version: 2.1
Name: asgi-s3
Version: 0.0.3
Summary: ASGI S3 storage
Home-page: https://github.com/erm/asgi-s3
Author: Jordan Eremieff
Author-email: jordan@eremieff.com
License: MIT
Platform: UNKNOWN
Classifier: License :: OSI Approved :: MIT License
Classifier: Operating System :: OS Independent
Classifier: Programming Language :: Python :: 3
Classifier: Programming Language :: Python :: 3.7
